.gitignore
LICENSE
README.md
pyproject.toml
.github/workflows/python-publish.yml
docs/Makefile
docs/abbrev_long.bib
docs/conf.py
docs/conf_overrides.py
docs/conf_spec.py
docs/index.rst
docs/make.bat
docs/references.bib
docs/_static/styles/my_theme.css
docs/_templates/autoapi/index.rst
docs/_templates/autoapi/python/attribute.rst
docs/_templates/autoapi/python/class.rst
docs/_templates/autoapi/python/data.rst
docs/_templates/autoapi/python/exception.rst
docs/_templates/autoapi/python/function.rst
docs/_templates/autoapi/python/method.rst
docs/_templates/autoapi/python/module.rst
docs/_templates/autoapi/python/package.rst
docs/_templates/autoapi/python/property.rst
src/boxlib/__init__.py
src/boxlib/_version.py
src/boxlib/boxlib.py
src/boxlib.egg-info/PKG-INFO
src/boxlib.egg-info/SOURCES.txt
src/boxlib.egg-info/dependency_links.txt
src/boxlib.egg-info/requires.txt
src/boxlib.egg-info/top_level.txt